{
    "table": "SALESHISTORY.OE_ORDER_HEADERS_ALL",
    "op_type": "U",
    "op_ts": "2019-05-20 21:20:21.003882",
    "current_ts": "2019-05-20T17:20:26.642001",
    "pos": "00000000080175145017",
    "before": {
        "HEADER_ID": 169307209,
        "ORG_ID": 1796,
        "ORDER_TYPE_ID": 1207,
        "ORDER_NUMBER": 149631614,
        "VERSION_NUMBER": 0,
        "EXPIRATION_DATE": null,
        "ORDER_SOURCE_ID": 0,
        "SOURCE_DOCUMENT_TYPE_ID": null,
        "ORIG_SYS_DOCUMENT_REF": "OE_ORDER_HEADERS_ALL169307209",
        "SOURCE_DOCUMENT_ID": null,
        "ORDERED_DATE": "2019-05-20 17:19:50",
        "REQUEST_DATE": "2019-05-20 17:19:50",
        "PRICING_DATE": "2019-05-20 17:19:40",
        "SHIPMENT_PRIORITY_CODE": null,
        "DEMAND_CLASS_CODE": null,
        "PRICE_LIST_ID": 6078511,
        "TAX_EXEMPT_FLAG": "S",
        "TAX_EXEMPT_NUMBER": null,
        "TAX_EXEMPT_REASON_CODE": null,
        "CONVERSION_RATE": null,
        "CONVERSION_TYPE_CODE": null,
        "CONVERSION_RATE_DATE": null,
        "PARTIAL_SHIPMENTS_ALLOWED": null,
        "SHIP_TOLERANCE_ABOVE": null,
        "SHIP_TOLERANCE_BELOW": null,
        "TRANSACTIONAL_CURR_CODE": "CAD",
        "AGREEMENT_ID": null,
        "TAX_POINT_CODE": null,
        "CUST_PO_NUMBER": null,
        "INVOICING_RULE_ID": null,
        "ACCOUNTING_RULE_ID": null,
        "PAYMENT_TERM_ID": 1650,
        "SHIPPING_METHOD_CODE": "000001_FEDEX_P_GND",
        "FREIGHT_CARRIER_CODE": "FEDEX",
        "FOB_POINT_CODE": null,
        "FREIGHT_TERMS_CODE": null,
        "SOLD_FROM_ORG_ID": 1796,
        "SOLD_TO_ORG_ID": 7407245,
        "SHIP_FROM_ORG_ID": 1846,
        "SHIP_TO_ORG_ID": 858700,
        "INVOICE_TO_ORG_ID": 858699,
        "DELIVER_TO_ORG_ID": null,
        "SOLD_TO_CONTACT_ID": null,
        "SHIP_TO_CONTACT_ID": null,
        "INVOICE_TO_CONTACT_ID": null,
        "DELIVER_TO_CONTACT_ID": null,
        "CREATION_DATE": "2019-05-20 17:20:04",
        "CREATED_BY": 82112,
        "LAST_UPDATED_BY": 82112,
        "LAST_UPDATE_DATE": "2019-05-20 17:20:04",
        "LAST_UPDATE_LOGIN": 853962981,
        "PROGRAM_APPLICATION_ID": null,
        "PROGRAM_ID": null,
        "PROGRAM_UPDATE_DATE": null,
        "REQUEST_ID": null,
        "CONTEXT": null,
        "ATTRIBUTE1": null,
        "ATTRIBUTE2": null,
        "ATTRIBUTE3": null,
        "ATTRIBUTE4": null,
        "ATTRIBUTE5": null,
        "ATTRIBUTE6": null,
        "ATTRIBUTE7": null,
        "ATTRIBUTE8": null,
        "ATTRIBUTE9": null,
        "ATTRIBUTE10": null,
        "ATTRIBUTE11": null,
        "ATTRIBUTE12": null,
        "ATTRIBUTE13": null,
        "ATTRIBUTE14": null,
        "ATTRIBUTE15": null,
        "GLOBAL_ATTRIBUTE_CATEGORY": null,
        "GLOBAL_ATTRIBUTE1": null,
        "GLOBAL_ATTRIBUTE2": null,
        "GLOBAL_ATTRIBUTE3": null,
        "GLOBAL_ATTRIBUTE4": null,
        "GLOBAL_ATTRIBUTE5": null,
        "GLOBAL_ATTRIBUTE6": null,
        "GLOBAL_ATTRIBUTE7": null,
        "GLOBAL_ATTRIBUTE8": null,
        "GLOBAL_ATTRIBUTE9": null,
        "GLOBAL_ATTRIBUTE10": null,
        "GLOBAL_ATTRIBUTE11": null,
        "GLOBAL_ATTRIBUTE12": null,
        "GLOBAL_ATTRIBUTE13": null,
        "GLOBAL_ATTRIBUTE14": null,
        "GLOBAL_ATTRIBUTE15": null,
        "GLOBAL_ATTRIBUTE16": null,
        "GLOBAL_ATTRIBUTE17": null,
        "GLOBAL_ATTRIBUTE18": null,
        "GLOBAL_ATTRIBUTE19": null,
        "GLOBAL_ATTRIBUTE20": null,
        "CANCELLED_FLAG": "N",
        "OPEN_FLAG": "Y",
        "BOOKED_FLAG": "N",
        "SALESREP_ID": 100189398,
        "RETURN_REASON_CODE": null,
        "ORDER_DATE_TYPE_CODE": null,
        "EARLIEST_SCHEDULE_LIMIT": null,
        "LATEST_SCHEDULE_LIMIT": null,
        "PAYMENT_TYPE_CODE": null,
        "PAYMENT_AMOUNT": null,
        "CHECK_NUMBER": null,
        "CREDIT_CARD_CODE": null,
        "CREDIT_CARD_HOLDER_NAME": null,
        "CREDIT_CARD_NUMBER": null,
        "CREDIT_CARD_EXPIRATION_DATE": null,
        "CREDIT_CARD_APPROVAL_CODE": null,
        "SALES_CHANNEL_CODE": null,
        "FIRST_ACK_CODE": null,
        "FIRST_ACK_DATE": null,
        "LAST_ACK_CODE": null,
        "LAST_ACK_DATE": null,
        "ORDER_CATEGORY_CODE": "ORDER",
        "CHANGE_SEQUENCE": null,
        "DROP_SHIP_FLAG": null,
        "CUSTOMER_PAYMENT_TERM_ID": null,
        "SHIPPING_INSTRUCTIONS": null,
        "PACKING_INSTRUCTIONS": null,
        "TP_CONTEXT": null,
        "TP_ATTRIBUTE1": null,
        "TP_ATTRIBUTE2": null,
        "TP_ATTRIBUTE3": null,
        "TP_ATTRIBUTE4": null,
        "TP_ATTRIBUTE5": null,
        "TP_ATTRIBUTE6": null,
        "TP_ATTRIBUTE7": null,
        "TP_ATTRIBUTE8": null,
        "TP_ATTRIBUTE9": null,
        "TP_ATTRIBUTE10": null,
        "TP_ATTRIBUTE11": null,
        "TP_ATTRIBUTE12": null,
        "TP_ATTRIBUTE13": null,
        "TP_ATTRIBUTE14": null,
        "TP_ATTRIBUTE15": null,
        "FLOW_STATUS_CODE": "ENTERED",
        "MARKETING_SOURCE_CODE_ID": null,
        "CREDIT_CARD_APPROVAL_DATE": null,
        "UPGRADED_FLAG": null,
        "CUSTOMER_PREFERENCE_SET_CODE": null,
        "BOOKED_DATE": null,
        "LOCK_CONTROL": 2,
        "PRICE_REQUEST_CODE": null,
        "BATCH_ID": null,
        "XML_MESSAGE_ID": 6469326,
        "ACCOUNTING_RULE_DURATION": null,
        "ATTRIBUTE16": null,
        "ATTRIBUTE17": null,
        "ATTRIBUTE18": null,
        "ATTRIBUTE19": null,
        "ATTRIBUTE20": null,
        "BLANKET_NUMBER": null,
        "SALES_DOCUMENT_TYPE_CODE": null,
        "SOLD_TO_PHONE_ID": null,
        "FULFILLMENT_SET_NAME": null,
        "LINE_SET_NAME": null,
        "DEFAULT_FULFILLMENT_SET": "N",
        "TRANSACTION_PHASE_CODE": "F",
        "SALES_DOCUMENT_NAME": null,
        "QUOTE_NUMBER": null,
        "QUOTE_DATE": null,
        "USER_STATUS_CODE": null,
        "DRAFT_SUBMITTED_FLAG": null,
        "SOURCE_DOCUMENT_VERSION_NUMBER": null,
        "SOLD_TO_SITE_USE_ID": null,
        "SUPPLIER_SIGNATURE": null,
        "SUPPLIER_SIGNATURE_DATE": null,
        "CUSTOMER_SIGNATURE": null,
        "CUSTOMER_SIGNATURE_DATE": null,
        "MINISITE_ID": null,
        "END_CUSTOMER_ID": null,
        "END_CUSTOMER_CONTACT_ID": null,
        "END_CUSTOMER_SITE_USE_ID": null,
        "IB_OWNER": null,
        "IB_CURRENT_LOCATION": null,
        "IB_INSTALLED_AT_LOCATION": null,
        "ORDER_FIRMED_DATE": null
    },
    "after": {
        "HEADER_ID": 169307209,
        "PRICE_REQUEST_CODE": "ONT-169307209"
    }
}